flask_typed_routes/__init__.py
flask_typed_routes/app.py
flask_typed_routes/core.py
flask_typed_routes/errors.py
flask_typed_routes/fields.py
flask_typed_routes/openapi.py
flask_typed_routes/utils.py
flask_typed_routes-0.2.7.dist-info/licenses/LICENSE
flask_typed_routes-0.2.7.dist-info/METADATA
flask_typed_routes-0.2.7.dist-info/WHEEL
flask_typed_routes-0.2.7.dist-info/top_level.txt
flask_typed_routes-0.2.7.dist-info/RECORD
