Metadata-Version: 2.4
Name: flask_typed_routes
Version: 0.2.7
Summary: Flask extension designed to effortlessly validate requests with Pydantic based on standard Python type hints.
Author-email: rmoralespp <rmoralespp@gmail.com>
License: MIT License
Project-URL: Source, https://github.com/rmoralespp/flask_typed_routes
Project-URL: Homepage, https://github.com/rmoralespp/flask_typed_routes
Project-URL: Changelog, https://github.com/rmoralespp/flask_typed_routes/blob/main/CHANGELOG.md
Project-URL: Issues, https://github.com/rmoralespp/flask_typed_routes/issues
Project-URL: Documentation, https://rmoralespp.github.io/flask_typed_routes/
Keywords: python,flask,pydantic,validation,extension,typing
Classifier: Environment :: Web Environment
Classifier: Operating System :: OS Independent
Classifier: Intended Audience :: Developers
Classifier: Intended Audience :: Information Technology
Classifier: Programming Language :: Python
Classifier: Programming Language :: Python :: 3 :: Only
Classifier: Programming Language :: Python :: 3.10
Classifier: Programming Language :: Python :: 3.11
Classifier: Programming Language :: Python :: 3.12
Classifier: Programming Language :: Python :: 3.13
Classifier: Topic :: Software Development :: Libraries :: Python Modules
Classifier: Topic :: Internet
Classifier: Topic :: Utilities
Classifier: Topic :: Internet :: WWW/HTTP :: Dynamic Content
Classifier: Framework :: Flask
Requires-Python: >=3.10
License-File: LICENSE
Requires-Dist: flask
Requires-Dist: pydantic<2.12.0
Dynamic: license-file
